Topsis_Tushar_402083001/__init__.py
Topsis_Tushar_402083001-1.0.1.dist-info/METADATA
Topsis_Tushar_402083001-1.0.1.dist-info/WHEEL
Topsis_Tushar_402083001-1.0.1.dist-info/top_level.txt
Topsis_Tushar_402083001-1.0.1.dist-info/RECORD
