Metadata-Version: 2.1
Name: Topsis-Tushar-402083001
Version: 1.0.1
Summary: A Python package for implementing TOPSIS
Author: Tushar Verma
Author-email: tusharverma643@gmail.com
License: MIT
Platform: UNKNOWN
Classifier: License :: OSI Approved :: MIT License
Classifier: Programming Language :: Python :: 3
Classifier: Programming Language :: Python :: 3.8
Requires-Dist: pandas
